spatialist/__init__.py
spatialist/ancillary.py
spatialist/auxil.py
spatialist/drivers_vector.yml
spatialist/envi.py
spatialist/multicore_helper.py
spatialist/raster.py
spatialist/sqlite_util.py
spatialist/vector.py
spatialist/install/install_deps.sh
spatialist/pkgs/mod_spatialite/mod_spatialite-4.3.0a-win-amd64.zip
spatialist/pkgs/mod_spatialite/mod_spatialite-4.3.0a-win-x86.zip
spatialist/tests/conftest.py
spatialist/tests/installtest_gdal_geos.py
spatialist/tests/installtest_ogr_sqlite.py
spatialist/tests/installtest_spatialite.py
spatialist/tests/test_ancillary.py
spatialist/tests/test_spatial.py
spatialist/tests/data/S1A__IW___A_20150309T173017_VV_grd_mli_geo_norm_db.tif
spatialist/tests/data/S1A__IW___D_20170309T054356_VV_grd_mli_geo_norm_db.tif
spatialist/tests/data/S1A__IW___D_20171210T054359_VV_grd_mli_geo_norm_db.tif
spatialist/tests/data/demo_finder.tar.xz
spatialist/tests/data/demo_finder.zip
spatialist/tests/data/demo_finder_noimplicit.zip
spatialist-0.16.1.dist-info/licenses/LICENSE.txt
spatialist-0.16.1.dist-info/METADATA
spatialist-0.16.1.dist-info/WHEEL
spatialist-0.16.1.dist-info/top_level.txt
spatialist-0.16.1.dist-info/RECORD
