Metadata-Version: 2.4
Name: spatialist
Version: 0.16.1
Summary: a Python module for spatial data handling
Maintainer-email: John Truckenbrodt <john.truckenbrodt@dlr.de>
License: # Copyright (c) 2015-2025, John Truckenbrodt
Project-URL: repository, https://github.com/johntruckenbrodt/spatialist
Project-URL: documentation, https://spatialist.readthedocs.io/en/latest/
Classifier: License :: OSI Approved :: MIT License
Classifier: Operating System :: Microsoft :: Windows
Classifier: Operating System :: POSIX :: Linux
Classifier: Programming Language :: Python :: 3
Requires-Python: >=3.8
License-File: LICENSE.txt
Requires-Dist: dill
Requires-Dist: geopandas
Requires-Dist: matplotlib
Requires-Dist: numpy
Requires-Dist: pandas
Requires-Dist: pathos>=0.2
Requires-Dist: progressbar2
Requires-Dist: pyyaml
Requires-Dist: shapely
Requires-Dist: tblib
Provides-Extra: test
Requires-Dist: pytest; extra == "test"
Provides-Extra: docs
Requires-Dist: sphinx; extra == "docs"
Dynamic: license-file
